setup.py
online_array/__init__.py
online_array/debug.py
online_array/online_array.py
online_array.egg-info/PKG-INFO
online_array.egg-info/SOURCES.txt
online_array.egg-info/dependency_links.txt
online_array.egg-info/top_level.txt