Metadata-Version: 1.1
Name: online-array
Version: 0.0.0
Summary: An array-like object that calls a function.
Home-page: https://git.lumc.nl/j.f.j.laros/online-array
Author: LUMC, Jeroen F.J. Laros
Author-email: J.F.J.Laros@lumc.nl
License: MIT License
Keywords: mathematics,numpy
Platform: any
Classifier: Development Status :: 3 - Alpha
Classifier: Intended Audience :: Science/Research
Classifier: Intended Audience :: Developers
Classifier: Operating System :: OS Independent
Classifier: Programming Language :: Python
Classifier: Topic :: Scientific/Engineering
